CHANGES.md
LICENSE
MANIFEST.in
README.md
requirements.txt
setup.py
nosey/__init__.py
nosey/command.py
nosey/watcher.py
nosey.egg-info/PKG-INFO
nosey.egg-info/SOURCES.txt
nosey.egg-info/dependency_links.txt
nosey.egg-info/entry_points.txt
nosey.egg-info/not-zip-safe
nosey.egg-info/requires.txt
nosey.egg-info/top_level.txt