Metadata-Version: 1.0
Name: nosey
Version: 0.1.2
Summary: Local continuous test runner with nose and watchdog.
Home-page: http://github.com/joeyespo/nosey
Author: Joe Esposito
Author-email: joe@joeyespo.com
License: MIT
Platform: any
